ssfMiscUtilities/__init__.py
ssfMiscUtilities/_modidx.py
ssfMiscUtilities/core.py
ssfMiscUtilities/generic.py
ssfMiscUtilities/lsf_interactive.py
ssfMiscUtilities-0.0.3.dist-info/LICENSE
ssfMiscUtilities-0.0.3.dist-info/METADATA
ssfMiscUtilities-0.0.3.dist-info/WHEEL
ssfMiscUtilities-0.0.3.dist-info/entry_points.txt
ssfMiscUtilities-0.0.3.dist-info/top_level.txt
ssfMiscUtilities-0.0.3.dist-info/RECORD
